{"timestamp":201811,"source":"SAPO","archive":"https://arquivo.pt/noFrame/replay/20181128183132/https://www.sapo.pt/noticias/economia/bolsa-de-xangai-encerra-a-perder-0-04_5bfd3288d405d3285915e205","id":1278458,"probability":0.51126814,"keywords":{"Qarabaq":1,"Angola":1,"PS":1,"Motores":1,"contribuição":2,"Ambiente":1,"Montijo":1,"Ricardo Salgado":1,"adesão":4,"Ajuda":1,"Proteção Civil":1,"serva":2,"Grupo Barraqueiro":1,"Glamour Tecnologia Motores":1,"Atenas":1,"Relação no processo Operação Marquês":1,"Natal":1,"Atualidade":1,"redução":2,"Bilheteira":1,"receber":2,"cheia":2,"Cabo Verde":1,"Desporto":1,"Xangai":1,"Shenzhen":1,"Viagens   ":1,"Tecnologia":1,"Farmácias   Folhetos   ":1,"Transferir":1,"CAF":1,"História de uma serva":1,"Moçambique":3,"Sporting":1,"Rede SAPO":1,"dose":4,"IVA":1,"MEO":1,"perder":2,"Universidade de Aveiro":1,"Montemor-o-Velho":1,"promulga":2,"Leslie":1,"Zoo":1,"recurso":2,"rede":2,"Lifestyle   Mail":1,"Bolsa de Xangai":1,"busca":2,"falar":2,"Santarém":1,"futebol":2,"Astrologia   Beleza":1,"bolsa":2,"abuso":2,"China":1,"Lifestyle":1,"AIMI":1,"Pesquisa   Saltar":1,"abrir":2,"prometer":2,"acreditar":2,"Ajax":1,"JMC":1,"subir":2,"praça":2,"PSI20":1,"Leiria":1,"SAPO":2,"continuação":2,"haver":2,"Emprego":1,"Animais   Apostas":1,"Costa":1,"condenar":2,"transição":2,"processo":2,"economia":4,"consultar":2,"censura":2,"Margaret Atwood":1,"escalão":2,"chuva":2,"MOCHE":1},"sentiment":0.51225775}
